odoo/addons/l10n_br_product_contract/README.rst
odoo/addons/l10n_br_product_contract/__init__.py
odoo/addons/l10n_br_product_contract/__manifest__.py
odoo/addons/l10n_br_product_contract/demo/contract_template.xml
odoo/addons/l10n_br_product_contract/demo/product.xml
odoo/addons/l10n_br_product_contract/demo/sale_order.xml
odoo/addons/l10n_br_product_contract/i18n/l10n_br_product_contract.pot
odoo/addons/l10n_br_product_contract/i18n/pt_BR.po
odoo/addons/l10n_br_product_contract/models/__init__.py
odoo/addons/l10n_br_product_contract/models/sale_order.py
odoo/addons/l10n_br_product_contract/models/sale_order_line.py
odoo/addons/l10n_br_product_contract/readme/CONFIGURE.md
odoo/addons/l10n_br_product_contract/readme/CONTRIBUTORS.md
odoo/addons/l10n_br_product_contract/readme/CREDITS.md
odoo/addons/l10n_br_product_contract/readme/DESCRIPTION.md
odoo/addons/l10n_br_product_contract/readme/HISTORY.md
odoo/addons/l10n_br_product_contract/readme/INSTALL.md
odoo/addons/l10n_br_product_contract/readme/USAGE.md
odoo/addons/l10n_br_product_contract/static/description/icon.png
odoo/addons/l10n_br_product_contract/static/description/index.html
odoo/addons/l10n_br_product_contract/tests/__init__.py
odoo/addons/l10n_br_product_contract/tests/test_l10n_br_product_contract.py
odoo_addon_l10n_br_product_contract-16.0.2.0.0.dist-info/METADATA
odoo_addon_l10n_br_product_contract-16.0.2.0.0.dist-info/WHEEL
odoo_addon_l10n_br_product_contract-16.0.2.0.0.dist-info/top_level.txt
odoo_addon_l10n_br_product_contract-16.0.2.0.0.dist-info/RECORD
