Metadata-Version: 2.1
Name: odoo-addon-l10n_br_product_contract
Version: 16.0.2.0.0
Requires-Python: >=3.10
Requires-Dist: odoo-addon-l10n_br_contract>=16.0dev,<16.1dev
Requires-Dist: odoo-addon-l10n_br_sale>=16.0dev,<16.1dev
Requires-Dist: odoo-addon-product_contract>=16.0dev,<16.1dev
Requires-Dist: odoo>=16.0a,<16.1dev
Summary: =?utf-8?q?Cria=C3=A7=C3=A3o_de_contratos_atrav=C3=A9s_dos_Pedidos_de_Vendas?=
Home-page: https://github.com/OCA/l10n-brazil
License: AGPL-3
Author: KMEE, Escodoo, Odoo Community Association (OCA)
Author-email: support@odoo-community.org
Classifier: Programming Language :: Python
Classifier: Framework :: Odoo
Classifier: Framework :: Odoo :: 16.0
Classifier: License :: OSI Approved :: GNU Affero General Public License v3
Classifier: Development Status :: 4 - Beta
